pyabricate/__init__.py
pyabricate/__main__.py
pyabricate/cli.py
pyabricate/py.typed
pyabricate/db/__init__.py
pyabricate/db/argannot.json.gz
pyabricate/db/card.json.gz
pyabricate/db/ecoh.json.gz
pyabricate/db/ecoli_vf.json.gz
pyabricate/db/megares.json.gz
pyabricate/db/ncbi.json.gz
pyabricate/db/plasmidfinder.json.gz
pyabricate/db/resfinder.json.gz
pyabricate/db/vfdb.json.gz
pyabricate-0.1.0.dist-info/licenses/COPYING
pyabricate-0.1.0.dist-info/METADATA
pyabricate-0.1.0.dist-info/WHEEL
pyabricate-0.1.0.dist-info/entry_points.txt
pyabricate-0.1.0.dist-info/top_level.txt
pyabricate-0.1.0.dist-info/RECORD
