Metadata-Version: 2.4
Name: pyabricate
Version: 0.1.0
Summary: A Python port of ABRicate, a tool for mass screening of contigs for antibiotic resistance and virulence genes.
Author-email: Martin Larralde <martin.larralde@embl.de>
License:                     GNU GENERAL PUBLIC LICENSE
Project-URL: Bug Tracker, https://github.com/althonos/pyabricate/issues
Project-URL: Changelog, https://github.com/althonos/pyabricate/blob/master/CHANGELOG.md
Project-URL: Coverage, https://codecov.io/gh/althonos/pyabricate/
Project-URL: Builds, https://github.com/althonos/pyabricate/actions
Project-URL: PyPI, https://pypi.org/project/pyabricate
Keywords: bioinformatics,antimicrobial,antibiotic,resistance
Classifier: Development Status :: 3 - Alpha
Classifier: Intended Audience :: Developers
Classifier: Intended Audience :: Science/Research
Classifier: License :: OSI Approved :: GNU General Public License v3 or later (GPLv3+)
Classifier: Operating System :: OS Independent
Classifier: Programming Language :: Python :: 3
Classifier: Topic :: Scientific/Engineering :: Bio-Informatics
Classifier: Topic :: Scientific/Engineering :: Medical Science Apps.
Classifier: Topic :: Software Development :: Libraries :: Python Modules
Classifier: Typing :: Typed
Requires-Python: >=3.7
License-File: COPYING
Requires-Dist: pyncbitk>=0.1.0-a5
Dynamic: license-file
